openunmix/__init__.py
openunmix/cli.py
openunmix/data.py
openunmix/evaluate.py
openunmix/filtering.py
openunmix/model.py
openunmix/predict.py
openunmix/transforms.py
openunmix/utils.py
tests/__init__.py
tests/create_vectors.py
tests/test_augmentations.py
tests/test_datasets.py
tests/test_io.py
tests/test_jit.py
tests/test_model.py
tests/test_regression.py
tests/test_transforms.py
tests/test_utils.py
tests/test_wiener.py
openunmix-1.2.1.dist-info/LICENSE
openunmix-1.2.1.dist-info/METADATA
openunmix-1.2.1.dist-info/WHEEL
openunmix-1.2.1.dist-info/entry_points.txt
openunmix-1.2.1.dist-info/top_level.txt
openunmix-1.2.1.dist-info/RECORD
