Metadata-Version: 2.1
Name: openunmix
Version: 1.2.1
Summary: PyTorch-based music source separation toolkit
Home-page: https://github.com/sigsep/open-unmix-pytorch
Author: Fabian-Robert Stöter
Author-email: fabian-robert.stoter@inria.fr
License: MIT
Platform: UNKNOWN
Classifier: Development Status :: 4 - Beta
Classifier: Programming Language :: Python :: 3
Classifier: Programming Language :: Python :: 3.6
Classifier: Programming Language :: Python :: 3.7
Classifier: Programming Language :: Python :: 3.8
Classifier: License :: OSI Approved :: MIT License
Classifier: Operating System :: OS Independent
Requires-Python: >=3.6
Provides-Extra: asteroid
Provides-Extra: tests
Provides-Extra: stempeg
Provides-Extra: evaluation
